{"1280958624042192958": {"1280029844809453613": {"love_points": 16, "emotions": {"\ucda9\uc131": 2, "\uacf5\uac10": 1, "\uc720\ucf8c": 1, "\uad11\uc2e0": 1, "\uacf5\ud3ec": 1, "\uc99d\uc624": 1}, "nickname": "\uc5d0\uc774\uc154 \uc624\ud3ec\ub4dc"}}, "1280789539073425430": {"1280029844809453613": {"love_points": 0, "emotions": {}, "nickname": "\uc5d0\uc774\uc154 \uc624\ud3ec\ub4dc"}, "1288390532812242990": {"love_points": 0, "emotions": {}}, "1285946172652916737": {"love_points": 0, "emotions": {}}, "1286208758338424874": {"love_points": 0, "emotions": {}, "nickname": "\ud2b8\uc70c\ub9ac \uc624\uc2a4\ub9cc\ud22c\uc2a4"}, "1286244341425246269": {"love_points": 0, "emotions": {}, "nickname": "\ud5ec\ub9ac\uc624\uc2a4 \ub370 \uc544\ub974\ub374\uc2a4"}}, "1280789443657338963": {"1280029844809453613": {"love_points": 21, "nickname": "\ub5a8\uc5b4\uc9c4 \ucc9c\uc0ac \uc5d0\uc774\uc154 \uc624\ud3ec\ub4dc", "emotions": {"\uc6b0\uc815": 1, "\uc874\uacbd": 1, "\ubd88\ucf8c": 1, "\uc720\ucf8c": 1, "\uad11\uc2e0": 1, "\ub3d9\uacbd": 1}}, "1285946172652916737": {"love_points": 0, "emotions": {"\ubcf4\ud638": 2, "\uc751\uc6d0": 1, "\uc874\uacbd": 1, "\uc720\ucf8c": 1, "\uc99d\uc624": 1, "\ubd88\uc2e0": 1, "\uc6b0\uc815": 1}, "nickname": "\uc5b4\ubd80 \ud0a4\ub9b4 \ub370 \ubc14\ubca8"}, "1286244341425246269": {"love_points": 0, "emotions": {"\uc720\ucf8c": 1}, "nickname": "\ud5ec\ub9ac\uc624\uc2a4 \ub370 \uc544\ub974\ub374\uc2a4"}, "1286208758338424874": {"love_points": 0, "emotions": {"\uc560\uc815": 1, "\uc548\ub77d": 1, "\ubcf4\ud638": 1}, "nickname": "\ud2b8\uc70c\ub9ac \uc624\uc2a4\ub9cc\ud22c\uc2a4"}, "1288390532812242990": {"love_points": 0, "nickname": "\uc54c\ub9ac\uc0e4 \ub9ac\ub4e0", "emotions": {"\ubcf4\ud638": 1, "\uacf5\uac10": 1}}, "1280800462827950123": {"love_points": 0, "emotions": {"\ubcf4\ud638": 1, "\ub3d9\uacbd": 1, "\ubd88\ucf8c": 1}, "nickname": "\uc774\ub4e0 \ud789\uc2a4"}, "1302940254076141641": {"love_points": 169, "emotions": {"\uc758\uc874": 1, "\uc2e4\ub9dd": 1, "\uc874\uacbd": 1, "\uc751\uc6d0": 1, "\ub3d9\uacbd": 1, "\uc0b4\uc758": 1}}, "1288141451653414973": {"love_points": 0, "nickname": "..."}}}